jse/__init__.py
jse/__main__.py
jse/bash.py
jse/editor.py
jse/entry.py
jse-0.1.4.dist-info/entry_points.txt
jse-0.1.4.dist-info/LICENSE
jse-0.1.4.dist-info/WHEEL
jse-0.1.4.dist-info/METADATA
jse-0.1.4.dist-info/RECORD
