Metadata-Version: 2.1
Name: jse
Version: 0.1.4
Summary: Quickly edit json files from the command line
Home-page: https://github.com/bjubes/jse
Author: Brian Jubelirer
Author-email: brian2386@gmail.com
Requires-Python: >=3.6,<4.0
Classifier: Programming Language :: Python :: 3
Classifier: Programming Language :: Python :: 3.10
Classifier: Programming Language :: Python :: 3.6
Classifier: Programming Language :: Python :: 3.7
Classifier: Programming Language :: Python :: 3.8
Classifier: Programming Language :: Python :: 3.9
Classifier: Topic :: Software Development
Classifier: Topic :: Text Processing
Classifier: Topic :: Utilities
Requires-Dist: click (>=8.0,<9.0)
Project-URL: Repository, https://github.com/bjubes/jse
